LICENSE
README.md
setup.cfg
setup.py
FastAPI_Skeleton.egg-info/PKG-INFO
FastAPI_Skeleton.egg-info/SOURCES.txt
FastAPI_Skeleton.egg-info/dependency_links.txt
FastAPI_Skeleton.egg-info/requires.txt
FastAPI_Skeleton.egg-info/top_level.txt
demo/main.py
demo/core/__init__.py
demo/core/config.py
demo/core/messages.py
demo/core/security.py
demo/modules/__init__.py
demo/modules/heart_beat/__init__.py
demo/modules/heart_beat/router/__init__.py
demo/modules/heart_beat/router/implement.py
demo/modules/heart_beat/schema/__init__.py
demo/modules/heart_beat/schema/heartbeat.py
demo/modules/heart_beat/service/__init__.py
demo/modules/heart_beat/service/implement.py
demo/modules/house_price/__init__.py
demo/modules/house_price/config.py
demo/modules/house_price/router/__init__.py
demo/modules/house_price/router/implement.py
demo/modules/house_price/schema/__init__.py
demo/modules/house_price/schema/payload.py
demo/modules/house_price/schema/prediction.py
demo/modules/house_price/service/__init__.py
demo/modules/house_price/service/implement.py
demo/modules_another/__init__.py
demo/modules_another/heart_beat_another/__init__.py
demo/modules_another/heart_beat_another/router/__init__.py
demo/modules_another/heart_beat_another/router/implement.py
demo/modules_another/heart_beat_another/schema/__init__.py
demo/modules_another/heart_beat_another/schema/heartbeat.py
demo/modules_another/heart_beat_another/service/__init__.py
demo/modules_another/heart_beat_another/service/implement.py
demo/modules_another/house_price_another/__init__.py
demo/modules_another/house_price_another/router/__init__.py
demo/modules_another/house_price_another/router/implement.py
demo/modules_another/house_price_another/schema/__init__.py
demo/modules_another/house_price_another/schema/payload.py
demo/modules_another/house_price_another/schema/prediction.py
demo/modules_another/house_price_another/service/__init__.py
demo/modules_another/house_price_another/service/implement.py
fastapi_modules/__init__.py
fastapi_modules/main.py
fastapi_modules/core/__init__.py
fastapi_modules/core/config.py
fastapi_modules/core/messages.py
fastapi_modules/core/security.py
fastapi_modules/ioc_container/__init__.py
